LICENSE.txt
README.md
setup.cfg
setup.py
ja/__init__.py
ja/__main__.py
ja/cmake.py
ja/frontend.pb
ja/frontend.py
ja/log.py
ja/native.py
ja.egg-info/PKG-INFO
ja.egg-info/SOURCES.txt
ja.egg-info/dependency_links.txt
ja.egg-info/entry_points.txt
ja.egg-info/requires.txt
ja.egg-info/top_level.txt